{
    "key": "group_61a789d372851",
    "title": "Contact",
    "fields": [
        {
            "key": "field_61a789dbf330b",
            "label": "Address",
            "name": "address",
            "type": "textarea",
            "instructions": "",
            "required": 0,
            "conditional_logic": 0,
            "wrapper": {
                "width": "",
                "class": "",
                "id": ""
            },
            "default_value": "",
            "placeholder": "",
            "maxlength": "",
            "rows": 3,
            "new_lines": "br"
        },
        {
            "key": "field_61a789e8f330c",
            "label": "Phone",
            "name": "phone",
            "type": "text",
            "instructions": "",
            "required": 0,
            "conditional_logic": 0,
            "wrapper": {
                "width": "",
                "class": "",
                "id": ""
            },
            "default_value": "",
            "placeholder": "",
            "prepend": "",
            "append": "",
            "maxlength": ""
        },
        {
            "key": "field_61a789ebf330d",
            "label": "Email",
            "name": "email",
            "type": "email",
            "instructions": "",
            "required": 0,
            "conditional_logic": 0,
            "wrapper": {
                "width": "",
                "class": "",
                "id": ""
            },
            "default_value": "",
            "placeholder": "",
            "prepend": "",
            "append": ""
        },
        {
            "key": "field_61a789f1f330e",
            "label": "Map Link",
            "name": "map_link",
            "type": "link",
            "instructions": "",
            "required": 0,
            "conditional_logic": 0,
            "wrapper": {
                "width": "",
                "class": "",
                "id": ""
            },
            "return_format": "array"
        }
    ],
    "location": [
        [
            {
                "param": "options_page",
                "operator": "==",
                "value": "acf-options-contact"
            }
        ]
    ],
    "menu_order": 0,
    "position": "normal",
    "style": "default",
    "label_placement": "top",
    "instruction_placement": "label",
    "hide_on_screen": "",
    "active": true,
    "description": "",
    "show_in_rest": 0,
    "modified": 1638369792
}